podaac/merger/__init__.py
podaac/merger/harmony/__init__.py
podaac/merger/harmony/cli.py
podaac/merger/harmony/download_worker.py
podaac/merger/harmony/service.py
podaac/merger/harmony/util.py
podaac/merger/merge.py
podaac/merger/merge_cli.py
podaac/merger/merge_worker.py
podaac/merger/path_utils.py
podaac/merger/preprocess_worker.py
podaac/merger/variable_info.py
podaac_concise-0.11.0.dist-info/METADATA
podaac_concise-0.11.0.dist-info/WHEEL
podaac_concise-0.11.0.dist-info/entry_points.txt
podaac_concise-0.11.0.dist-info/licenses/LICENSE
podaac_concise-0.11.0.dist-info/RECORD
