Metadata-Version: 2.4
Name: podaac-concise
Version: 0.11.0
Summary: Harmony service that merges granules
License: Apache-2.0
License-File: LICENSE
Author: podaac-tva
Author-email: podaac-tva@jpl.nasa.gov
Requires-Python: >=3.12,<4.0
Classifier: License :: OSI Approved :: Apache Software License
Classifier: Programming Language :: Python :: 3
Classifier: Programming Language :: Python :: 3.12
Classifier: Programming Language :: Python :: 3.13
Classifier: Programming Language :: Python :: 3.14
Classifier: Topic :: Software Development :: Libraries :: Python Modules
Requires-Dist: harmony-service-lib (>=2.11.0,<3.0.0)
Requires-Dist: importlib-metadata (>=8.5.0,<9.0.0)
Requires-Dist: netCDF4 (>=1.5.6,<2.0.0)
Requires-Dist: numpy (>=2.1.3,<3.0.0)
Project-URL: Repository, https://github.com/podaac/concise
